hbayesdm/__init__.py
hbayesdm/base.py
hbayesdm/diagnostics.py
hbayesdm/models/__init__.py
hbayesdm/models/_alt_delta.py
hbayesdm/models/_alt_gamma.py
hbayesdm/models/_bandit2arm_delta.py
hbayesdm/models/_bandit4arm2_kalman_filter.py
hbayesdm/models/_bandit4arm_2par_lapse.py
hbayesdm/models/_bandit4arm_4par.py
hbayesdm/models/_bandit4arm_lapse.py
hbayesdm/models/_bandit4arm_lapse_decay.py
hbayesdm/models/_bandit4arm_singleA_lapse.py
hbayesdm/models/_bart_ewmv.py
hbayesdm/models/_bart_par4.py
hbayesdm/models/_cgt_cm.py
hbayesdm/models/_choiceRT_ddm.py
hbayesdm/models/_choiceRT_ddm_single.py
hbayesdm/models/_cra_exp.py
hbayesdm/models/_cra_linear.py
hbayesdm/models/_dbdm_prob_weight.py
hbayesdm/models/_dd_cs.py
hbayesdm/models/_dd_cs_single.py
hbayesdm/models/_dd_exp.py
hbayesdm/models/_dd_hyperbolic.py
hbayesdm/models/_dd_hyperbolic_single.py
hbayesdm/models/_gng_m1.py
hbayesdm/models/_gng_m2.py
hbayesdm/models/_gng_m3.py
hbayesdm/models/_gng_m4.py
hbayesdm/models/_igt_orl.py
hbayesdm/models/_igt_pvl_decay.py
hbayesdm/models/_igt_pvl_delta.py
hbayesdm/models/_igt_vpp.py
hbayesdm/models/_peer_ocu.py
hbayesdm/models/_prl_ewa.py
hbayesdm/models/_prl_fictitious.py
hbayesdm/models/_prl_fictitious_multipleB.py
hbayesdm/models/_prl_fictitious_rp.py
hbayesdm/models/_prl_fictitious_rp_woa.py
hbayesdm/models/_prl_fictitious_woa.py
hbayesdm/models/_prl_rp.py
hbayesdm/models/_prl_rp_multipleB.py
hbayesdm/models/_pst_Q.py
hbayesdm/models/_pst_gainloss_Q.py
hbayesdm/models/_ra_noLA.py
hbayesdm/models/_ra_noRA.py
hbayesdm/models/_ra_prospect.py
hbayesdm/models/_rdt_happiness.py
hbayesdm/models/_task2AFC_sdt.py
hbayesdm/models/_ts_par4.py
hbayesdm/models/_ts_par6.py
hbayesdm/models/_ts_par7.py
hbayesdm/models/_ug_bayes.py
hbayesdm/models/_ug_delta.py
hbayesdm/models/_wcs_sql.py
hbayesdm/preprocess_funcs.py
hbayesdm-1.1.0.dist-info/WHEEL
hbayesdm-1.1.0.dist-info/METADATA
hbayesdm-1.1.0.dist-info/RECORD
