Metadata-Version: 2.1
Name: hbayesdm
Version: 1.1.0
Summary: Python interface for hBayesDM, hierarchical Bayesian modeling of RL-DM tasks
Home-page: https://github.com/CCS-Lab/hBayesDM
License: GPLv3
Author: hBayesDM developers
Author-email: hbayesdm-users@googlegroups.com
Requires-Python: >=3.6.1
Classifier: Intended Audience :: Science/Research
Classifier: License :: OSI Approved :: GNU General Public License v3 (GPLv3)
Classifier: License :: Other/Proprietary License
Classifier: Programming Language :: Python :: 3
Classifier: Programming Language :: Python :: 3 :: Only
Classifier: Programming Language :: Python :: 3.6
Classifier: Programming Language :: Python :: 3.7
Classifier: Programming Language :: Python :: 3.8
Classifier: Programming Language :: Python :: 3.9
Requires-Dist: arviz (>=0.10.0,<0.11.0)
Requires-Dist: importlib-metadata (>=3.3.0,<4.0.0)
Requires-Dist: matplotlib (>=3.3.3,<4.0.0)
Requires-Dist: numpy (>=1.19.4,<2.0.0)
Requires-Dist: pandas (>=1.1.5,<2.0.0)
Requires-Dist: pystan (>=2.19.1,<3.0.0)
Requires-Dist: scipy (>=1.5.4,<2.0.0)
Project-URL: Documentation, http://hbayesdm.readthedocs.io/
Project-URL: Repository, https://github.com/CCS-Lab/hBayesDM
